pylama/__init__.py
pylama/__main__.py
pylama/check_async.py
pylama/config.py
pylama/config_toml.py
pylama/context.py
pylama/core.py
pylama/errors.py
pylama/hook.py
pylama/main.py
pylama/pytest.py
pylama/utils.py
pylama/libs/__init__.py
pylama/libs/inirama.py
pylama/lint/__init__.py
pylama/lint/pylama_eradicate.py
pylama/lint/pylama_fake.py
pylama/lint/pylama_mccabe.py
pylama/lint/pylama_mypy.py
pylama/lint/pylama_pycodestyle.py
pylama/lint/pylama_pydocstyle.py
pylama/lint/pylama_pyflakes.py
pylama/lint/pylama_pylint.py
pylama/lint/pylama_radon.py
pylama/lint/pylama_vulture.py
pylama-8.4.1.dist-info/LICENSE
pylama-8.4.1.dist-info/METADATA
pylama-8.4.1.dist-info/WHEEL
pylama-8.4.1.dist-info/entry_points.txt
pylama-8.4.1.dist-info/top_level.txt
pylama-8.4.1.dist-info/RECORD
