Metadata-Version: 2.1
Name: pylama
Version: 8.4.1
Summary: Code audit tool for python
Home-page: https://github.com/klen/pylama
Author: Kirill Klenov
Author-email: horneds@gmail.com
License: MIT
Project-URL: Documentation, https://klen.github.io/pylama
Project-URL: Source code, https://github.com/klen/pylama
Project-URL: Issue tracker, https://github.com/klen/pylama/issues
Keywords: qa,linter,pydocstyle,pycodestyle,mccabe,pylint
Platform: UNKNOWN
Classifier: Development Status :: 5 - Production/Stable
Classifier: Environment :: Console
Classifier: Intended Audience :: Developers
Classifier: Intended Audience :: System Administrators
Classifier: License :: OSI Approved :: MIT License
Classifier: Programming Language :: Python
Classifier: Programming Language :: Python :: 3
Classifier: Programming Language :: Python :: 3.10
Classifier: Programming Language :: Python :: 3.7
Classifier: Programming Language :: Python :: 3.8
Classifier: Programming Language :: Python :: 3.9
Classifier: Topic :: Software Development :: Quality Assurance
Classifier: Topic :: Software Development :: Testing
Requires-Python: >=3.7
Provides-Extra: tests
Provides-Extra: all
Provides-Extra: pylint
Provides-Extra: eradicate
Provides-Extra: radon
Provides-Extra: mypy
Provides-Extra: vulture
Provides-Extra: toml
License-File: LICENSE
